{
  "_fv": 43,
  "_type": "rangeditem",
  "definition": {
    "renderType": 0,
    "texture": "aaa",
    "customModelName": "Normal",
    "name": "Black Spectral Arrow",
    "specialInfo": [],
    "creativeTab": {
      "value": "CUSTOM:Weapon"
    },
    "stackSize": 64,
    "ammoItem": {
      "value": ""
    },
    "shootConstantly": false,
    "usageCount": 0,
    "actionSound": {
      "value": "entity.arrow.shoot"
    },
    "hasGlow": true,
    "animation": "spear",
    "enableMeleeDamage": false,
    "damageVsEntity": 0.0,
    "bulletPower": 1.0,
    "bulletDamage": 5.0,
    "bulletKnockback": 0,
    "bulletParticles": false,
    "bulletIgnitesFire": false,
    "bulletItemTexture": {
      "value": ""
    },
    "bulletModel": "Modelblack_spectral_arrow_Converted",
    "customBulletModelTexture": "black_spectral_arrow.png"
  }
}