{
  "_fv": 43,
  "_type": "tool",
  "definition": {
    "renderType": 0,
    "texture": "aa",
    "customModelName": "Normal",
    "name": "Item Weaponsword",
    "specialInfo": [],
    "creativeTab": {
      "value": "No creative tab entry"
    },
    "toolType": "Sword",
    "harvestLevel": 10,
    "efficiency": 10.0,
    "attackSpeed": 3.0,
    "enchantability": 9,
    "damageVsEntity": 10.0,
    "usageCount": 0,
    "blocksAffected": [],
    "hasGlow": true,
    "repairItems": [],
    "immuneToFire": false,
    "stayInGridWhenCrafting": false,
    "damageOnCrafting": false
  }
}