{
  "_fv": 43,
  "_type": "armor",
  "definition": {
    "enableHelmet": true,
    "textureHelmet": "evoker_helmet",
    "enableBody": true,
    "textureBody": "pillager_chestplet",
    "enableLeggings": true,
    "textureLeggings": "pillager_leggins",
    "enableBoots": true,
    "textureBoots": "snow_villager_boots",
    "onBootsTick": {
      "name": "PillagerArmorbutunoMeiteitukunoibento"
    },
    "creativeTab": {
      "value": "CUSTOM:Armor"
    },
    "armorTextureFile": "pillager_",
    "helmetName": "Pillager Armor Helmet",
    "bodyName": "Pillager Armor Chestplate",
    "leggingsName": "Pillager Armor Leggins",
    "bootsName": "Pillager Armor Boots",
    "helmetSpecialInfo": [],
    "bodySpecialInfo": [],
    "leggingsSpecialInfo": [],
    "bootsSpecialInfo": [],
    "helmetModelName": "Modelbanner_Converted",
    "helmetModelPart": "hlmet",
    "helmetModelTexture": "banner.png",
    "bodyModelName": "Modelpillager_Converted",
    "bodyModelPart": "body",
    "armsModelPartL": "left_arm",
    "armsModelPartR": "right_arm",
    "bodyModelTexture": "pillager.png",
    "leggingsModelName": "Modelpillager_Converted",
    "leggingsModelPartL": "left_leg",
    "leggingsModelPartR": "right_leg",
    "leggingsModelTexture": "pillager.png",
    "bootsModelName": "Default",
    "bootsModelPartL": "Boots L",
    "bootsModelPartR": "Boots R",
    "bootsModelTexture": "From armor",
    "helmetItemRenderType": 1,
    "helmetItemCustomModelName": "banneritemconverted:default",
    "bodyItemRenderType": 0,
    "bodyItemCustomModelName": "Normal",
    "leggingsItemRenderType": 0,
    "leggingsItemCustomModelName": "Normal",
    "bootsItemRenderType": 0,
    "bootsItemCustomModelName": "Normal",
    "helmetImmuneToFire": false,
    "bodyImmuneToFire": false,
    "leggingsImmuneToFire": false,
    "bootsImmuneToFire": false,
    "maxDamage": 0,
    "damageValueHelmet": 0,
    "damageValueBody": 6,
    "damageValueLeggings": 5,
    "damageValueBoots": 2,
    "enchantability": 9,
    "toughness": 0.0,
    "knockbackResistance": 0.0,
    "equipSound": {
      "value": "item.armor.equip_leather"
    },
    "repairItems": []
  }
}